gcloud_aio_pubsub_fsg-1.1.3-py3.8-nspkg.pth
gcloud/aio/pubsub/__init__.py
gcloud/aio/pubsub/subscriber_client.py
gcloud/aio/pubsub/utils.py
tests/integration/__init__.py
tests/integration/conftest.py
tests/integration/constructor_test.py
tests/unit/__init__.py
tests/unit/subscription_test.py
gcloud_aio_pubsub_fsg-1.1.3.dist-info/LICENSE
gcloud_aio_pubsub_fsg-1.1.3.dist-info/METADATA
gcloud_aio_pubsub_fsg-1.1.3.dist-info/WHEEL
gcloud_aio_pubsub_fsg-1.1.3.dist-info/namespace_packages.txt
gcloud_aio_pubsub_fsg-1.1.3.dist-info/top_level.txt
gcloud_aio_pubsub_fsg-1.1.3.dist-info/RECORD
