Metadata-Version: 2.1
Name: gcloud-aio-pubsub-fsg
Version: 1.1.3
Summary: Asyncio Python Client for Google Cloud Pub/Sub
Home-page: https://github.com/fsgsmartbuildings/gcloud-aio
Author: Facility Solutions Group
License: MIT License
Platform: Posix; MacOS X; Windows
Classifier: Development Status :: 5 - Production/Stable
Classifier: Intended Audience :: Developers
Classifier: License :: OSI Approved :: MIT License
Classifier: Operating System :: OS Independent
Classifier: Programming Language :: Python :: 3
Classifier: Programming Language :: Python :: 3.6
Classifier: Programming Language :: Python :: 3.7
Classifier: Programming Language :: Python :: 3.8
Classifier: Topic :: Internet
Requires-Python: >= 3.6
Requires-Dist: google-cloud-pubsub (<2.0.0,>=0.29.4)
